setup.cfg
setup.py
crfst/__init__.py
crfst/canonical.py
crfst/eval.py
crfst/features.py
crfst/ftex.py
crfst/readers.py
crfst/tagger.py
crfst/testis.py
crfst/testis2.py
crfst/utils.py
crfst/winfeatures.py
crfst.egg-info/.pypirc
crfst.egg-info/PKG-INFO
crfst.egg-info/SOURCES.txt
crfst.egg-info/dependency_links.txt
crfst.egg-info/requires.txt
crfst.egg-info/top_level.txt