Metadata-Version: 1.1
Name: crfst
Version: 0.2
Summary: A multi-purpose sequential tagger wrapped around CRFSuite
Home-page: https://github.com/savkov/CRFSuiteTagger
Author: Aleksandar Savkov
Author-email: aleksandar@savkov.eu
License: GPLv3
Keywords: CRF CRFSuite sequence tagging POS chunking NER
Platform: Unix
Platform: MacOS
Classifier: Development Status :: 3 - Alpha
Classifier: License :: OSI Approved :: GNU General Public License v3 (GPLv3)
